{"cameraMode":{"drawMode":0,"name":"Shaded","section":"Shading Mode"},"sceneLighting":true,"audioPlay":false,"sceneViewState":{"m_AlwaysRefresh":false,"showFog":true,"showSkybox":true,"showFlares":true,"showImageEffects":true,"showParticleSystems":true,"showVisualEffectGraphs":true,"m_FxEnabled":true},"in2DMode":false,"pivot":{"x":4.173209190368652,"y":35.32155227661133,"z":0.11437927186489105},"rotation":{"x":-0.11430492997169495,"y":0.716335117816925,"z":-0.12045928835868836,"w":-0.6779379844665527},"size":1.224744200706482,"orthographic":false}